README.md
setup.py
apt_repo/__init__.py
apt_repo/test_apt_repo.py
apt_repo.egg-info/PKG-INFO
apt_repo.egg-info/SOURCES.txt
apt_repo.egg-info/dependency_links.txt
apt_repo.egg-info/top_level.txt