Metadata-Version: 2.1
Name: apt-repo
Version: 0.5
Summary: Python library to query APT repositories
Home-page: https://github.com/brennerm/python-apt-repo
Author: brennerm
Author-email: xamrennerb@gmail.com
License: MIT
Platform: UNKNOWN
Requires-Python: >=3.5
